paodate.py
zato_ext_paodate-1.3.dist-info/METADATA
zato_ext_paodate-1.3.dist-info/WHEEL
zato_ext_paodate-1.3.dist-info/top_level.txt
zato_ext_paodate-1.3.dist-info/RECORD
