Metadata-Version: 2.1
Name: zato-ext-paodate
Version: 1.3
Summary: Easy object-oriented date and time handling for Python
Home-page: https://github.com/danielgtaylor/paodate
Download-URL: https://github.com/danielgtaylor/paodate/zipball/master
Author: Daniel G. Taylor
Author-email: dan@programmer-art.org
Keywords: date time timespan sql
Platform: Platform Independent
Provides: paodate
